swag/__init__.py
swag/__main__.py
swag/colors.py
swag/install.py
swag/swaggy.py
swag-2.0.5.dist-info/COPYING
swag-2.0.5.dist-info/LICENSE.txt
swag-2.0.5.dist-info/METADATA
swag-2.0.5.dist-info/WHEEL
swag-2.0.5.dist-info/entry_points.txt
swag-2.0.5.dist-info/RECORD
