Metadata-Version: 2.1
Name: swag
Version: 2.0.5
Summary: Swag up your shell output with escape code magic!
Home-page: https://github.com/4thel00z/swag
License: GPL-3
Author: 4thel00z
Author-email: 4thel00z@gmail.com
Requires-Python: >=3.6,<4.0
Classifier: License :: Other/Proprietary License
Classifier: Programming Language :: Python :: 3
Classifier: Programming Language :: Python :: 3.6
Classifier: Programming Language :: Python :: 3.7
Classifier: Programming Language :: Python :: 3.8
Classifier: Programming Language :: Python :: 3.9
Classifier: Programming Language :: Python :: 3.10
Classifier: Programming Language :: Python :: 3.11
Requires-Dist: typer (>=0.3.2,<0.4.0)
